promptimizer/__init__.py
promptimizer/client.py
promptimizer/prompt/__init__.py
promptimizer/prompt/builder_prompt.py
promptimizer/prompt/optimizer_prompt.py
promptimizer/prompt_builder.py
promptimizer/prompt_optimizer.py
promptimizer/utils/__init__.py
promptimizer/utils/color_print.py
promptimizer-0.1.0.dist-info/entry_points.txt
promptimizer-0.1.0.dist-info/METADATA
promptimizer-0.1.0.dist-info/WHEEL
promptimizer-0.1.0.dist-info/RECORD
