Metadata-Version: 2.1
Name: promptimizer
Version: 0.1.0
Summary: An elegant LLM prompt optimizer and prompt builder.
Home-page: https://github.com/Undertone0809/promptimizer
License: MIT
Author: Zeeland
Author-email: zeeland@foxmail.com
Requires-Python: >=3.8
Classifier: License :: OSI Approved :: MIT License
Classifier: Programming Language :: Python :: 3
Classifier: Programming Language :: Python :: 3.8
Classifier: Programming Language :: Python :: 3.9
Classifier: Programming Language :: Python :: 3.10
Classifier: Programming Language :: Python :: 3.11
Requires-Dist: click (>=8.1.7,<9.0.0)
Requires-Dist: promptulate (>=1.7.2,<2.0.0)
Requires-Dist: questionary (>=2.0.1,<3.0.0)
Project-URL: Repository, https://github.com/Undertone0809/promptimizer
